algogears/__init__.py
algogears/chain.py
algogears/core.py
algogears/dynamic_hull.py
algogears/graham.py
algogears/jarvis.py
algogears/kd_tree.py
algogears/preparata.py
algogears/quickhull.py
algogears/slab.py
tests/__init__.py
tests/algorithms/__init__.py
tests/algorithms/test_chain.py
tests/algorithms/test_dynamic_hull.py
tests/algorithms/test_graham.py
tests/algorithms/test_jarvis.py
tests/algorithms/test_kd_tree.py
tests/algorithms/test_preparata.py
tests/algorithms/test_quickhull.py
tests/algorithms/test_slab.py
tests/entities/__init__.py
tests/entities/test_avl_tree.py
tests/entities/test_bin_tree.py
tests/entities/test_bin_tree_node.py
tests/entities/test_graph.py
tests/entities/test_graph_edge.py
tests/entities/test_oriented_graph.py
tests/entities/test_oriented_graph_edge.py
tests/entities/test_oriented_planar_straight_line_graph.py
tests/entities/test_oriented_planar_straight_line_graph_edge.py
tests/entities/test_planar_straight_line_graph.py
tests/entities/test_planar_straight_line_graph_edge.py
tests/entities/test_threaded_bin_tree.py
tests/entities/test_turn.py
tests/serialization/__init__.py
tests/serialization/test_core.py
tests/serialization/test_dynamic_hull.py
tests/serialization/test_graham.py
tests/serialization/test_preparata.py
tests/serialization/test_quickhull.py
algogears-1.1.3.dist-info/LICENSE
algogears-1.1.3.dist-info/METADATA
algogears-1.1.3.dist-info/WHEEL
algogears-1.1.3.dist-info/top_level.txt
algogears-1.1.3.dist-info/RECORD
