Metadata-Version: 2.1
Name: algogears
Version: 1.1.3
Summary: This library contains implementations of computational geometry algorithms in Python3 adapted for educational purposes.
Author: artandfi (Artem Fisunenko)
Author-email: artem.fisunenko@hotmail.com
Keywords: Python3,computational geometry,convex hull,region search,geometric search,point location,proximity,closest pair,closest points
Classifier: Programming Language :: Python :: 3
Classifier: Operating System :: OS Independent
License-File: LICENSE
